voltdbclient.py
voltdbclient-14.2.0.dist-info/METADATA
voltdbclient-14.2.0.dist-info/WHEEL
voltdbclient-14.2.0.dist-info/top_level.txt
voltdbclient-14.2.0.dist-info/RECORD
