Metadata-Version: 2.4
Name: voltdbclient
Version: 14.2.0
Summary: VoltDB python client
Author-email: Volt Active Data <support@voltactivedata.com>
Project-URL: Homepage, https://www.voltactivedata.com/
Classifier: License :: OSI Approved :: MIT License
Classifier: Programming Language :: Python
Classifier: Programming Language :: Python :: 3
Requires-Python: >=3.9
Provides-Extra: extras
Requires-Dist: pyjks; extra == "extras"
Requires-Dist: cryptography; extra == "extras"
Requires-Dist: python-gssapi; extra == "extras"
